mstatistics/__init__.py
mstatistics/statistics.py
mstatistics/rgr/__init__.py
mstatistics/rgr/regression.py
mstatistics/rgr/tests/__init__.py
mstatistics/rgr/tests/test_regression.py
mstatistics/tests/__init__.py
mstatistics/tests/test_statistics.py
mstatistics-0.1.2.post1.dist-info/LICENSE
mstatistics-0.1.2.post1.dist-info/METADATA
mstatistics-0.1.2.post1.dist-info/WHEEL
mstatistics-0.1.2.post1.dist-info/top_level.txt
mstatistics-0.1.2.post1.dist-info/RECORD
